odoo/addons/product_documentation_set/README.rst
odoo/addons/product_documentation_set/__init__.py
odoo/addons/product_documentation_set/__manifest__.py
odoo/addons/product_documentation_set/i18n/it.po
odoo/addons/product_documentation_set/i18n/product_documentation_set.pot
odoo/addons/product_documentation_set/models/__init__.py
odoo/addons/product_documentation_set/models/product_category.py
odoo/addons/product_documentation_set/models/product_documentation_set.py
odoo/addons/product_documentation_set/models/product_template.py
odoo/addons/product_documentation_set/readme/CONFIGURE.rst
odoo/addons/product_documentation_set/readme/CONTRIBUTORS.rst
odoo/addons/product_documentation_set/readme/DESCRIPTION.rst
odoo/addons/product_documentation_set/readme/USAGE.rst
odoo/addons/product_documentation_set/security/product_documentation_set.xml
odoo/addons/product_documentation_set/static/description/icon.png
odoo/addons/product_documentation_set/static/description/index.html
odoo/addons/product_documentation_set/tests/__init__.py
odoo/addons/product_documentation_set/tests/test_product_doc.py
odoo/addons/product_documentation_set/views/product_category.xml
odoo/addons/product_documentation_set/views/product_documentation_set.xml
odoo/addons/product_documentation_set/views/product_template.xml
odoo12_addon_product_documentation_set-12.0.1.0.0.99.dev5.dist-info/METADATA
odoo12_addon_product_documentation_set-12.0.1.0.0.99.dev5.dist-info/WHEEL
odoo12_addon_product_documentation_set-12.0.1.0.0.99.dev5.dist-info/top_level.txt
odoo12_addon_product_documentation_set-12.0.1.0.0.99.dev5.dist-info/RECORD
